organizedpointfilters_pybind.cp36-win_amd64.pyd
organizedpointfilters/__init__.py
organizedpointfilters/cuda/__init__.py
organizedpointfilters/cuda/bilateral.cu
organizedpointfilters/cuda/kernel.py
organizedpointfilters/cuda/laplacian.cu
organizedpointfilters/cuda/laplacian_check.cu
organizedpointfilters/utility/__init__.py
organizedpointfilters/utility/helper.py
organizedpointfilters/utility/o3d_util.py
organizedpointfilters-0.2.3.dist-info/LICENSE
organizedpointfilters-0.2.3.dist-info/METADATA
organizedpointfilters-0.2.3.dist-info/WHEEL
organizedpointfilters-0.2.3.dist-info/top_level.txt
organizedpointfilters-0.2.3.dist-info/RECORD
