Metadata-Version: 2.1
Name: organizedpointfilters
Version: 0.2.3
Summary: A collection of fitlers for organized point clouds. Laplacian, bilateral, and other filters.
Home-page: https://github.com/JeremyBYU/OrganizedPointFilters
Author: Jeremy Castagno
Author-email: jeremybyu@gmail.com
License: MIT
Platform: UNKNOWN
